aiohtml2pdf/__init__.py
aiohtml2pdf/browser.py
aiohtml2pdf/pages.py
aiohtml2pdf-0.1.0a1.dist-info/WHEEL
aiohtml2pdf-0.1.0a1.dist-info/METADATA
aiohtml2pdf-0.1.0a1.dist-info/RECORD
