Metadata-Version: 2.1
Name: aiohtml2pdf
Version: 0.1.0a1
Summary: 
Author: Albert Khachatryan
Author-email: ht.albert2606@gmail.com
Requires-Python: >=3.8,<4.0
Classifier: Programming Language :: Python :: 3
Classifier: Programming Language :: Python :: 3.8
Classifier: Programming Language :: Python :: 3.9
Requires-Dist: pyppeteer (>=1.0.2,<2.0.0)
